{
    "movieInfoResult": {
        "movieInfo": {
            "movieCd": "20231460",
            "movieNm": "남편 상사에게 몸으로 내조하는 아내",
            "movieNmEn": "",
            "movieNmOg": "",
            "showTm": "64",
            "prdtYear": "2023",
            "openDt": "20230503",
            "prdtStatNm": "개봉",
            "typeNm": "장편",
            "nations": [
                {
                    "nationNm": "한국"
                }
            ],
            "genres": [
                {
                    "genreNm": "성인물(에로)"
                }
            ],
            "directors": [
                {
                    "peopleNm": "핑마",
                    "peopleNmEn": ""
                }
            ],
            "actors": [],
            "showTypes": [
                {
                    "showTypeGroupNm": "2D",
                    "showTypeNm": "디지털"
                }
            ],
            "companys": [
                {
                    "companyCd": "20229104",
                    "companyNm": "와이제이스토리",
                    "companyNmEn": "YJ story",
                    "companyPartNm": "제작사"
                },
                {
                    "companyCd": "20229104",
                    "companyNm": "와이제이스토리",
                    "companyNmEn": "YJ story",
                    "companyPartNm": "배급사"
                }
            ],
            "audits": [
                {
                    "auditNo": "2023-MF01114 ",
                    "watchGradeNm": "청소년관람불가"
                }
            ],
            "staffs": []
        },
        "source": "영화진흥위원회"
    }
}