{
    "movieInfoResult": {
        "movieInfo": {
            "movieCd": "20211541",
            "movieNm": "스프린터",
            "movieNmEn": "Sprinter",
            "movieNmOg": "",
            "showTm": "86",
            "prdtYear": "2022",
            "openDt": "20230524",
            "prdtStatNm": "개봉",
            "typeNm": "장편",
            "nations": [
                {
                    "nationNm": "한국"
                }
            ],
            "genres": [
                {
                    "genreNm": "기타"
                }
            ],
            "directors": [
                {
                    "peopleNm": "최승연",
                    "peopleNmEn": "CHOI Seungyeun"
                }
            ],
            "actors": [
                {
                    "peopleNm": "박성일",
                    "peopleNmEn": "PARK Sung-il",
                    "cast": "",
                    "castEn": ""
                },
                {
                    "peopleNm": "공민정",
                    "peopleNmEn": "GONG Min-jeong",
                    "cast": "",
                    "castEn": ""
                },
                {
                    "peopleNm": "임지호",
                    "peopleNmEn": "Lim Ji-Ho",
                    "cast": "",
                    "castEn": ""
                },
                {
                    "peopleNm": "전신환",
                    "peopleNmEn": "JEON Sin-hwan",
                    "cast": "",
                    "castEn": ""
                },
                {
                    "peopleNm": "송덕호",
                    "peopleNmEn": "",
                    "cast": "",
                    "castEn": ""
                },
                {
                    "peopleNm": "최준혁",
                    "peopleNmEn": "Choe Jun-hyeok",
                    "cast": "",
                    "castEn": ""
                },
                {
                    "peopleNm": "한태경",
                    "peopleNmEn": "Han taekyong",
                    "cast": "1번 레인",
                    "castEn": ""
                }
            ],
            "showTypes": [
                {
                    "showTypeGroupNm": "2D",
                    "showTypeNm": "디지털"
                },
                {
                    "showTypeGroupNm": "2D",
                    "showTypeNm": "디지털 영문자막"
                }
            ],
            "companys": [
                {
                    "companyCd": "20141789",
                    "companyNm": "영화사 만화경",
                    "companyNmEn": "",
                    "companyPartNm": "제작사"
                },
                {
                    "companyCd": "20239901",
                    "companyNm": "스튜디오 에이드",
                    "companyNmEn": "",
                    "companyPartNm": "배급사"
                }
            ],
            "audits": [
                {
                    "auditNo": "2022-MF03317 ",
                    "watchGradeNm": "12세이상관람가"
                }
            ],
            "staffs": [
                {
                    "peopleNm": "최민철",
                    "peopleNmEn": "",
                    "staffRoleNm": "프로듀서"
                },
                {
                    "peopleNm": "최승연",
                    "peopleNmEn": "CHOI Seungyeun",
                    "staffRoleNm": "시나리오(각본)"
                }
            ]
        },
        "source": "영화진흥위원회"
    }
}