{
    "movieInfoResult": {
        "movieInfo": {
            "movieCd": "20224755",
            "movieNm": "나는 마을 방과후 교사입니다",
            "movieNmEn": "The Teachers: pink, nature trail, ridge between rice paddies, plum",
            "movieNmOg": "",
            "showTm": "94",
            "prdtYear": "2022",
            "openDt": "20230111",
            "prdtStatNm": "개봉",
            "typeNm": "장편",
            "nations": [
                {
                    "nationNm": "한국"
                }
            ],
            "genres": [
                {
                    "genreNm": "다큐멘터리"
                }
            ],
            "directors": [
                {
                    "peopleNm": "박홍열",
                    "peopleNmEn": "PARK Hongyeol"
                },
                {
                    "peopleNm": "황다은",
                    "peopleNmEn": "HWANG Daeun"
                }
            ],
            "actors": [],
            "showTypes": [
                {
                    "showTypeGroupNm": "2D",
                    "showTypeNm": "디지털"
                },
                {
                    "showTypeGroupNm": "2D",
                    "showTypeNm": "디지털 영문자막"
                }
            ],
            "companys": [
                {
                    "companyCd": "20229113",
                    "companyNm": "(주)스튜디오그레인풀",
                    "companyNmEn": "grainfull",
                    "companyPartNm": "제작사"
                },
                {
                    "companyCd": "20229113",
                    "companyNm": "(주)스튜디오그레인풀",
                    "companyNmEn": "grainfull",
                    "companyPartNm": "배급사"
                }
            ],
            "audits": [
                {
                    "auditNo": "2022-MF03072",
                    "watchGradeNm": "전체관람가"
                }
            ],
            "staffs": []
        },
        "source": "영화진흥위원회"
    }
}