{
    "movieInfoResult": {
        "movieInfo": {
            "movieCd": "20226808",
            "movieNm": "사랑하는 남편을 위한 불륜",
            "movieNmEn": "",
            "movieNmOg": "愛する夫の為-夫の上司に犯●れた私-経堂里穂",
            "showTm": "64",
            "prdtYear": "2022",
            "openDt": "20220901",
            "prdtStatNm": "개봉",
            "typeNm": "장편",
            "nations": [
                {
                    "nationNm": "일본"
                }
            ],
            "genres": [
                {
                    "genreNm": "성인물(에로)"
                }
            ],
            "directors": [
                {
                    "peopleNm": "카와이 조지",
                    "peopleNmEn": ""
                }
            ],
            "actors": [],
            "showTypes": [
                {
                    "showTypeGroupNm": "2D",
                    "showTypeNm": "디지털"
                }
            ],
            "companys": [
                {
                    "companyCd": "20100142",
                    "companyNm": "(주)씨맥스커뮤니케이션즈",
                    "companyNmEn": "",
                    "companyPartNm": "배급사"
                }
            ],
            "audits": [
                {
                    "auditNo": "2022-MF02043 ",
                    "watchGradeNm": "청소년관람불가"
                }
            ],
            "staffs": []
        },
        "source": "영화진흥위원회"
    }
}