{
    "movieInfoResult": {
        "movieInfo": {
            "movieCd": "20228855",
            "movieNm": "특공여전사",
            "movieNmEn": "Rescue",
            "movieNmOg": "绝色营救",
            "showTm": "99",
            "prdtYear": "2019",
            "openDt": "20221226",
            "prdtStatNm": "개봉",
            "typeNm": "장편",
            "nations": [
                {
                    "nationNm": "중국"
                }
            ],
            "genres": [
                {
                    "genreNm": "액션"
                }
            ],
            "directors": [],
            "actors": [],
            "showTypes": [
                {
                    "showTypeGroupNm": "2D",
                    "showTypeNm": "디지털"
                }
            ],
            "companys": [
                {
                    "companyCd": "20192401",
                    "companyNm": "초코필름",
                    "companyNmEn": "",
                    "companyPartNm": "배급사"
                }
            ],
            "audits": [
                {
                    "auditNo": "2022-MF02928",
                    "watchGradeNm": "15세이상관람가"
                }
            ],
            "staffs": []
        },
        "source": "영화진흥위원회"
    }
}