{
    "movieInfoResult": {
        "movieInfo": {
            "movieCd": "20205443",
            "movieNm": "나일 강의 죽음",
            "movieNmEn": "Death on the Nile",
            "movieNmOg": "",
            "showTm": "126",
            "prdtYear": "2021",
            "openDt": "20220209",
            "prdtStatNm": "개봉",
            "typeNm": "장편",
            "nations": [
                {
                    "nationNm": "미국"
                }
            ],
            "genres": [
                {
                    "genreNm": "범죄"
                },
                {
                    "genreNm": "드라마"
                },
                {
                    "genreNm": "미스터리"
                }
            ],
            "directors": [
                {
                    "peopleNm": "케네스 브래너",
                    "peopleNmEn": "Kenneth Branagh"
                }
            ],
            "actors": [
                {
                    "peopleNm": "케네스 브래너",
                    "peopleNmEn": "Kenneth Branagh",
                    "cast": "",
                    "castEn": ""
                },
                {
                    "peopleNm": "갤 가돗",
                    "peopleNmEn": "Gal Gadot",
                    "cast": "",
                    "castEn": ""
                },
                {
                    "peopleNm": "아미 해머",
                    "peopleNmEn": "Armie Hammer",
                    "cast": "",
                    "castEn": ""
                },
                {
                    "peopleNm": "에마 매키",
                    "peopleNmEn": "Emma Mackey",
                    "cast": "",
                    "castEn": ""
                }
            ],
            "showTypes": [
                {
                    "showTypeGroupNm": "2D",
                    "showTypeNm": "디지털"
                },
                {
                    "showTypeGroupNm": "DOLBYCINEMA",
                    "showTypeNm": "DOLBYCINEMA"
                }
            ],
            "companys": [
                {
                    "companyCd": "20161801",
                    "companyNm": "월트디즈니컴퍼니코리아 유한책임회사",
                    "companyNmEn": "The Walt Disney Company Korea",
                    "companyPartNm": "배급사"
                },
                {
                    "companyCd": "20161801",
                    "companyNm": "월트디즈니컴퍼니코리아 유한책임회사",
                    "companyNmEn": "The Walt Disney Company Korea",
                    "companyPartNm": "수입사"
                }
            ],
            "audits": [
                {
                    "auditNo": "2022-MF00215",
                    "watchGradeNm": "12세이상관람가"
                }
            ],
            "staffs": []
        },
        "source": "영화진흥위원회"
    }
}