{
    "movieInfoResult": {
        "movieInfo": {
            "movieCd": "20211545",
            "movieNm": "흐르다",
            "movieNmEn": "On the Sand House",
            "movieNmOg": "",
            "showTm": "122",
            "prdtYear": "2021",
            "openDt": "20230329",
            "prdtStatNm": "개봉",
            "typeNm": "장편",
            "nations": [
                {
                    "nationNm": "한국"
                }
            ],
            "genres": [
                {
                    "genreNm": "드라마"
                }
            ],
            "directors": [
                {
                    "peopleNm": "김현정",
                    "peopleNmEn": "KIM Hyunjung"
                }
            ],
            "actors": [
                {
                    "peopleNm": "이설",
                    "peopleNmEn": "LEE Sul",
                    "cast": "",
                    "castEn": ""
                },
                {
                    "peopleNm": "박지수",
                    "peopleNmEn": "PARK Ji-soo",
                    "cast": "동사무소 직원",
                    "castEn": ""
                }
            ],
            "showTypes": [
                {
                    "showTypeGroupNm": "2D",
                    "showTypeNm": "디지털"
                },
                {
                    "showTypeGroupNm": "2D",
                    "showTypeNm": "디지털 영문자막"
                }
            ],
            "companys": [
                {
                    "companyCd": "20230321",
                    "companyNm": "영화문",
                    "companyNmEn": "",
                    "companyPartNm": "제작사"
                },
                {
                    "companyCd": "20168613",
                    "companyNm": "M&M 인터내셔널",
                    "companyNmEn": "M&M International",
                    "companyPartNm": "배급사"
                }
            ],
            "audits": [
                {
                    "auditNo": "2023-MF00555",
                    "watchGradeNm": "12세이상관람가"
                }
            ],
            "staffs": []
        },
        "source": "영화진흥위원회"
    }
}