{
    "movieInfoResult": {
        "movieInfo": {
            "movieCd": "20231873",
            "movieNm": "음욕의 교육",
            "movieNmEn": "",
            "movieNmOg": "留年した息子を惑わすHカップ義母　織田真子",
            "showTm": "60",
            "prdtYear": "2022",
            "openDt": "20230601",
            "prdtStatNm": "개봉",
            "typeNm": "장편",
            "nations": [
                {
                    "nationNm": "일본"
                }
            ],
            "genres": [
                {
                    "genreNm": "성인물(에로)"
                },
                {
                    "genreNm": "멜로/로맨스"
                }
            ],
            "directors": [
                {
                    "peopleNm": "사쿠라비토",
                    "peopleNmEn": ""
                }
            ],
            "actors": [],
            "showTypes": [
                {
                    "showTypeGroupNm": "2D",
                    "showTypeNm": "디지털"
                }
            ],
            "companys": [
                {
                    "companyCd": "20174841",
                    "companyNm": "(주)가온콘텐츠",
                    "companyNmEn": "",
                    "companyPartNm": "배급사"
                }
            ],
            "audits": [
                {
                    "auditNo": "2023-MF01364 ",
                    "watchGradeNm": "청소년관람불가"
                }
            ],
            "staffs": []
        },
        "source": "영화진흥위원회"
    }
}