{
    "movieInfoResult": {
        "movieInfo": {
            "movieCd": "20231229",
            "movieNm": "메탈리카: 72 시즌스",
            "movieNmEn": "Metallica: 72 Seasons",
            "movieNmOg": "",
            "showTm": "114",
            "prdtYear": "2023",
            "openDt": "20230413",
            "prdtStatNm": "개봉",
            "typeNm": "장편",
            "nations": [
                {
                    "nationNm": "미국"
                }
            ],
            "genres": [
                {
                    "genreNm": "공연"
                }
            ],
            "directors": [
                {
                    "peopleNm": "팀 색센티",
                    "peopleNmEn": "Tim Saccenti"
                }
            ],
            "actors": [],
            "showTypes": [
                {
                    "showTypeGroupNm": "2D",
                    "showTypeNm": "디지털"
                }
            ],
            "companys": [
                {
                    "companyCd": "20203082",
                    "companyNm": "씨제이포디플렉스 주식회사",
                    "companyNmEn": "",
                    "companyPartNm": "배급사"
                }
            ],
            "audits": [
                {
                    "auditNo": "2023-MF00931",
                    "watchGradeNm": "12세이상관람가"
                }
            ],
            "staffs": []
        },
        "source": "영화진흥위원회"
    }
}